src/__init__.py
src/datasetUtils.py
src/getAndMergeDatasets.py
src/splitDataset.py
datasetManipulation-0.1.dist-info/METADATA
datasetManipulation-0.1.dist-info/WHEEL
datasetManipulation-0.1.dist-info/entry_points.txt
datasetManipulation-0.1.dist-info/top_level.txt
datasetManipulation-0.1.dist-info/RECORD
