Metadata-Version: 2.1
Name: datasetManipulation
Version: 0.1
Summary: Naia Science dataset Manipulation utils
Author: Axelle Lorin for Naia Science
Requires-Dist: roboflow ==0.2.29
Requires-Dist: ultralytics ==8.0.196
Requires-Dist: pycocotools
Requires-Dist: split-folders
